{"article_一文读懂事件冒泡与事件捕获.md":"qzVsIz48","article_【字节跳动】前端面试题总结.md":"BMUtOAfs","project_smartwordbreak_log_index.md":"vl1UYGUY","project_smartwordbreak_statement_index.md":"DwhOA0Jo","self_index.md":"YZPMt2Ak","works_contribution.md":"82ewoLop","article_深入vue3源码，看看vue.use后究竟发生了什么？.md":"DLeWiWDv","note_mysql.md":"D9R6scl-","article_一文读懂伪类与伪元素.md":"Z9g60aeg","article_浅析defineproperty与proxy实现的双向绑定.md":"DjHNKYwR","article_【用友金融】前端面试题总结.md":"BAguBX-8","works_opensource.md":"CpzdcJfF","article_从0实现一个年度报告.md":"fn1hwDQO","note_javascript.md":"BMSgMBzr","project_clipboardmanager_statement_index.md":"CevBYZfa","index.md":"BPhr-L4T","project_jsrunner_index.md":"CUQpyrYq","note_ssr.md":"C5wQvh1o","project_clipboardmanager_guide_index.md":"CeKelMsL","demos_promiseify-post-message_inner.md":"CmPVrAz_","project_jsrunner_log_index.md":"C6NdXWce","article_深入理解浏览器运行原理.md":"MrEjaSX2","project_clipboardmanager_index.md":"BubkaA0P","article_彻底搞懂对象的数据属性描述符、存储属性描述符.md":"CrFxKFSU","project_markdown_shortcut_index.md":"C53aR7D0","demos_promiseify-post-message_index.md":"D5dAeSHG","note_react router.md":"BpikA3LZ","article_一文读懂函数中this指向问题.md":"CCq5yMe1","project_smartwordbreak_index.md":"C0nh3TdS","project_markdown_log_index.md":"DS4-Qd_g","article_深入理解proxy与reflect.md":"Ckcw0EgD","note_redux.md":"B8S-beaW","article_深入javascript数据类型.md":"DnJ3tGMI","article_【2023】青训营 - 前端练习题汇总解析.md":"gzWkmhaj","article_【快手】深入理解前端面试题.md":"CjszsReO","project_markdown_index.md":"Bo_nTvxA","note_react hooks.md":"Dsj11_-g","note_css.md":"4YjmLbNc","article_深入理解浏览器缓存机制.md":"NU8GHnL3","project_clipboardmanager_log_index.md":"DdvKALtJ","note_front-end engineering.md":"CXN1RkHs","note_javascriptenhanced.md":"ClDXjXdL","note_react.md":"7eeKsU1c"}
