{"note_ssr.md":"94f87cd4","project_clipboardmanager_guide_index.md":"dc45e2e1","project_clipboardmanager_index.md":"646f61a5","project_clipboardmanager_log_index.md":"168b06f5","project_clipboardmanager_statement_index.md":"d5b513df","project_clipboardmanager_vip_index.md":"236faa3c","article_【字节跳动】前端面试题总结.md":"9b258235","article_【快手】深入理解前端面试题.md":"097dddc2","article_一文读懂函数中this指向问题.md":"d127f8dc","article_从0实现一个年度报告.md":"205298c6","article_【2023】青训营 - 前端练习题汇总解析.md":"e7c3ab14","project_markdown_shortcut_index.md":"c296a49a","project_smartwordbreak_index.md":"38670b11","project_smartwordbreak_log_index.md":"1377d1f0","project_smartwordbreak_statement_index.md":"816a4d49","self_index.md":"afdcc2c7","works_contribution.md":"0e338d0c","works_opensource.md":"ca69b139","project_markdown_index.md":"b6494016","article_彻底搞懂对象的数据属性描述符、存储属性描述符.md":"3aac21e7","article_浅析defineproperty与proxy实现的双向绑定.md":"1ef9a3a3","article_深入javascript数据类型.md":"80fefc4d","article_深入vue3源码，看看vue.use后究竟发生了什么？.md":"47b27afb","article_深入理解proxy与reflect.md":"0cb30df0","article_深入理解浏览器缓存机制.md":"de8a5acf","article_深入理解浏览器运行原理.md":"17ac4d03","index.md":"0df3f55b","note_javascript.md":"cb1fb5ee","note_css.md":"d6a0c3c4","note_front-end engineering.md":"47f147a3","article_一文读懂事件冒泡与事件捕获.md":"a1377acc","article_【用友金融】前端面试题总结.md":"212cfb3c","article_一文读懂伪类与伪元素.md":"64758185","note_javascriptenhanced.md":"8feb320c"}
