{"article_【字节跳动】前端面试题总结.md":"f9664a76","article_【快手】深入理解前端面试题.md":"66336ec2","article_【2023】青训营 - 前端练习题汇总解析.md":"2e39d3e9","article_【用友金融】前端面试题总结.md":"535e5750","article_浅析defineproperty与proxy实现的双向绑定.md":"aba5abb6","article_一文读懂事件冒泡与事件捕获.md":"e5a6cba0","article_一文读懂伪类与伪元素.md":"53af0be9","article_一文读懂函数中this指向问题.md":"36dc3cd7","note_front-end engineering.md":"da71c933","article_从0实现一个年度报告.md":"a2a93516","article_深入理解浏览器缓存机制.md":"cbb18c87","index.md":"9f59f66c","article_深入javascript数据类型.md":"a85382c6","article_深入vue3源码，看看vue.use后究竟发生了什么？.md":"81b1c96f","article_彻底搞懂对象的数据属性描述符、存储属性描述符.md":"ca1958c4","project_smartwordbreak_log_index.md":"072f3324","article_深入理解浏览器运行原理.md":"76bb276a","project_clipboardmanager_index.md":"e373d73b","project_clipboardmanager_statement_index.md":"54b6f669","project_clipboardmanager_log_index.md":"66fa8116","project_clipboardmanager_vip_index.md":"652c99bd","project_smartwordbreak_index.md":"8d365478","works_opensource.md":"56e36299","project_smartwordbreak_statement_index.md":"4eef3d1f","self_index.md":"2de50bc3","works_contribution.md":"9ccebf76","note_javascript.md":"64844917","note_ssr.md":"de51f49e","article_深入理解proxy与reflect.md":"fe0a030d","project_clipboardmanager_guide_index.md":"9f46fa80","note_css.md":"37ffa470","note_javascriptenhanced.md":"db27d4c2"}
