{"note_javascript.md":"b0728f64","article_【2023】青训营 - 前端练习题汇总解析.md":"8f2f5a4b","article_【字节跳动】前端面试题总结.md":"8151fb54","article_【快手】深入理解前端面试题.md":"cc922afb","article_【用友金融】前端面试题总结.md":"45372ab3","note_ssr.md":"c6a93b12","article_从0实现一个年度报告.md":"b13acd04","note_css.md":"c81cfec5","project_clipboardmanager_vip_index.md":"904b36ca","project_clipboardmanager_statement_index.md":"d363dc40","project_jsrunner_index.md":"525038d5","project_jsrunner_log_index.md":"2df72bd8","project_markdown_index.md":"64f478ce","project_markdown_log_index.md":"090231aa","project_markdown_shortcut_index.md":"f0dea204","project_smartwordbreak_log_index.md":"27f30190","project_smartwordbreak_statement_index.md":"96a0d359","self_index.md":"a93b54ea","works_contribution.md":"c412c229","article_彻底搞懂对象的数据属性描述符、存储属性描述符.md":"e9000655","article_一文读懂事件冒泡与事件捕获.md":"84a30874","works_opensource.md":"6d6c9f56","article_一文读懂伪类与伪元素.md":"c6aea36f","project_smartwordbreak_index.md":"807bcdc9","article_一文读懂函数中this指向问题.md":"462ed0f1","article_浅析defineproperty与proxy实现的双向绑定.md":"05521da5","article_深入javascript数据类型.md":"6612d7c3","article_深入vue3源码，看看vue.use后究竟发生了什么？.md":"adfe8c7b","article_深入理解浏览器运行原理.md":"39da977c","index.md":"757ecb4b","article_深入理解proxy与reflect.md":"8ba129a5","note_front-end engineering.md":"9114f9bb","project_clipboardmanager_guide_index.md":"581b6364","article_深入理解浏览器缓存机制.md":"8c601f78","project_clipboardmanager_index.md":"29d02261","project_clipboardmanager_log_index.md":"a9cc0f8f","note_react.md":"bcacc28d","note_javascriptenhanced.md":"c067733b"}
