{"article_彻底搞懂对象的数据属性描述符、存储属性描述符.md":"65f5f178","article_深入vue3源码，看看vue.use后究竟发生了什么？.md":"72692388","index.md":"dc597d99","article_从0实现一个年度报告.md":"444ed443","article_一文读懂事件冒泡与事件捕获.md":"ed0709b3","article_一文读懂伪类与伪元素.md":"1ee23a7e","article_一文读懂函数中this指向问题.md":"b12d0931","article_深入理解浏览器缓存机制.md":"ec0f7cbc","article_深入理解浏览器运行原理.md":"98a7beb6","article_深入理解proxy与reflect.md":"adcfc6ce","note_javascript.md":"25b801b6","article_【2023】青训营 - 前端练习题汇总解析.md":"ee082f74","note_front-end engineering.md":"30580588","note_css.md":"f2c44a85","project_clipboardmanager_index.md":"4505462a","project_clipboardmanager_guide_index.md":"9be057b1","self_index.md":"4e106b01","project_clipboardmanager_statement_index.md":"a7eaee73","project_clipboardmanager_vip_index.md":"5bbd9efe","project_smartwordbreak_index.md":"6085ce67","project_smartwordbreak_log_index.md":"e663df49","project_smartwordbreak_statement_index.md":"381c24e5","works_opensource.md":"180d0ac9","works_contribution.md":"b0d70239","project_clipboardmanager_log_index.md":"ee42b264","note_javascriptenhanced.md":"fbbf7b3d"}
